src/ahb_slave.sv
`timescale 1ns/1ps

module ahb_slave (
    input  logic        HCLK,
    input  logic        HRESETn,
    input  logic [31:0] HADDR,
    input  logic        HWRITE,
    input  logic [1:0]  HTRANS,
    input  logic [2:0]  HSIZE,
    input  logic [2:0]  HBURST,
    input  logic [31:0] HWDATA,
    input  logic        HSEL,
    
    output logic        HREADYOUT,
    output logic [31:0] HRDATA,
    output logic        HRESP
);

    logic [31:0] mem [0:255]; // small memory for testing
    
    logic [31:0] addr_reg;
    logic        write_reg;
    logic        active_transfer;
    logic [1:0]  wait_cnt;

    always_ff @(posedge HCLK or negedge HRESETn) begin
        if (!HRESETn) begin
            addr_reg <= 0;
            write_reg <= 0;
            active_transfer <= 0;
            HREADYOUT <= 1;
            HRESP <= 0;
            HRDATA <= 0;
            wait_cnt <= 0;
        end else begin
            // check invalid address for error response (TC5)
            if (HSEL && (HTRANS == 2'b10 || HTRANS == 2'b11) && HADDR > 32'h03FC) begin
                HRESP <= 1;
                HREADYOUT <= 1;
                active_transfer <= 0;
            end 
            else begin
                HRESP <= 0;
                
                // capture address phase
                if (HSEL && HREADYOUT && (HTRANS == 2'b10 || HTRANS == 2'b11)) begin
                    addr_reg <= HADDR;
                    write_reg <= HWRITE;
                    active_transfer <= 1;
                    
                    // insert wait state for specific address (TC3)
                    if (HADDR == 32'h0020) begin
                        HREADYOUT <= 0;
                        wait_cnt <= 2; 
                    end
                end
                
                // execute data phase
                if (active_transfer) begin
                    if (wait_cnt > 0) begin
                        wait_cnt <= wait_cnt - 1;
                        if (wait_cnt == 1) HREADYOUT <= 1;
                    end else begin
                        if (write_reg)
                            mem[addr_reg[9:2]] <= HWDATA;
                        else
                            HRDATA <= mem[addr_reg[9:2]];
                            
                        active_transfer <= 0;
                    end
                end
            end
        end
    end
endmodule

src/ahb_tb.sv
`timescale 1ns/1ps

module ahb_tb;
    logic        HCLK;
    logic        HRESETn;
    logic [31:0] HADDR;
    logic        HWRITE;
    logic [1:0]  HTRANS;
    logic [2:0]  HSIZE;
    logic [2:0]  HBURST;
    logic [31:0] HWDATA;
    logic        HSEL;
    logic        HREADY;
    logic [31:0] HRDATA;
    logic        HRESP;

    ahb_slave dut (.*, .HREADYOUT(HREADY));

    initial begin
        HCLK = 0;
        forever #5 HCLK = ~HCLK;
    end

    initial begin
        $dumpfile("ahb_sim.vcd");
        $dumpvars(0, ahb_tb);
        
        HRESETn = 0; HSEL = 0; HADDR = 0; HWRITE = 0; HTRANS = 0;
        HSIZE = 3'b010; HBURST = 0; HWDATA = 0;
        
        #15 HRESETn = 1;
        
        // tc1: single write
        @(posedge HCLK);
        HSEL = 1; HADDR = 32'h0004; HWRITE = 1; HTRANS = 2'b10;
        @(posedge HCLK);
        HTRANS = 2'b00; 
        HWDATA = 32'hAABBCCDD;
        wait(HREADY);
        
        // tc2: single read
        @(posedge HCLK);
        HADDR = 32'h0004; HWRITE = 0; HTRANS = 2'b10;
        @(posedge HCLK);
        HTRANS = 2'b00;
        wait(HREADY);
        $display("read data: %h", HRDATA);
        
        // tc3: write with wait states
        @(posedge HCLK);
        HADDR = 32'h0020; HWRITE = 1; HTRANS = 2'b10;
        @(posedge HCLK);
        HTRANS = 2'b00;
        HWDATA = 32'h12345678;
        wait(HREADY); 
        
        // tc4: incr4 burst
        @(posedge HCLK);
        HBURST = 3'b011; 
        HADDR = 32'h0100; HWRITE = 1; HTRANS = 2'b10; 
        
        @(posedge HCLK);
        HADDR = 32'h0104; HTRANS = 2'b11;
        HWDATA = 32'h11111111;
        
        @(posedge HCLK);
        HADDR = 32'h0108; HTRANS = 2'b11;
        HWDATA = 32'h22222222;
        
        @(posedge HCLK);
        HADDR = 32'h010C; HTRANS = 2'b11;
        HWDATA = 32'h33333333;
        
        @(posedge HCLK);
        HTRANS = 2'b00;
        HWDATA = 32'h44444444;
        
        // tc5: invalid address error
        @(posedge HCLK);
        HBURST = 3'b000;
        HADDR = 32'hFFFFFFFF; HWRITE = 0; HTRANS = 2'b10;
        @(posedge HCLK);
        HTRANS = 2'b00;
        wait(HREADY);
        if (HRESP == 1) $display("error working");

        #20 $finish;
    end
endmodule

sim/ahb_sim.vcd
$date
	Sun Aug 23 20:15:20 2026
$end
$version
	Icarus Verilog
$end
$timescale
	1ps
$end
$scope module ahb_tb $end
$var wire 1 ! HRESP $end
$var wire 1 " HREADY $end
$var wire 32 # HRDATA [31:0] $end
$var reg 32 $ HADDR [31:0] $end
$var reg 3 % HBURST [2:0] $end
$var reg 1 & HCLK $end
$var reg 1 ' HRESETn $end
$var reg 1 ( HSEL $end
$var reg 3 ) HSIZE [2:0] $end
$var reg 2 * HTRANS [1:0] $end
$var reg 32 + HWDATA [31:0] $end
$var reg 1 , HWRITE $end
$scope module dut $end
$var wire 32 - HADDR [31:0] $end
$var wire 3 . HBURST [2:0] $end
$var wire 1 & HCLK $end
$var wire 1 ' HRESETn $end
$var wire 1 ( HSEL $end
$var wire 3 / HSIZE [2:0] $end
$var wire 2 0 HTRANS [1:0] $end
$var wire 32 1 HWDATA [31:0] $end
$var wire 1 , HWRITE $end
$var reg 32 2 HRDATA [31:0] $end
$var reg 1 " HREADYOUT $end
$var reg 1 ! HRESP $end
$var reg 1 3 active_transfer $end
$var reg 32 4 addr_reg [31:0] $end
$var reg 2 5 wait_cnt [1:0] $end
$var reg 1 6 write_reg $end
$upscope $end
$upscope $end
$enddefinitions $end
$comment Show the parameter values. $end
$dumpall
$end
#0
$dumpvars
06
b0 5
b0 4
03
b0 2
b0 1
b0 0
b10 /
b0 .
b0 -
0,
b0 +
b0 *
b10 )
0(
0'
0&
b0 %
b0 $
b0 #
1"
0!
$end
#5000
1&
#10000
0&
#15000
13
16
b100 4
b10 *
b10 0
1,
b100 $
b100 -
1(
1&
1'
#20000
0&
#25000
03
b10101010101110111100110011011101 +
b10101010101110111100110011011101 1
b0 *
b0 0
1&
#30000
0&
#35000
13
06
b10 *
b10 0
0,
1&
#40000
0&
#45000
03
b10101010101110111100110011011101 #
b10101010101110111100110011011101 2
b0 *
b0 0
1&
#50000
0&
#55000
b10 5
0"
13
16
b100000 4
b10 *
b10 0
1,
b100000 $
b100000 -
1&
#60000
0&
#65000
b1 5
b10010001101000101011001111000 +
b10010001101000101011001111000 1
b0 *
b0 0
1&
#70000
0&
#75000
1"
b0 5
1&
#80000
0&
#85000
03
b100000000 4
b10 *
b10 0
b100000000 $
b100000000 -
b11 %
b11 .
1&
#90000
0&
#95000
13
b100000100 4
b10001000100010001000100010001 +
b10001000100010001000100010001 1
b11 *
b11 0
b100000100 $
b100000100 -
1&
#100000
0&
#105000
03
b100001000 4
b100010001000100010001000100010 +
b100010001000100010001000100010 1
b100001000 $
b100001000 -
1&
#110000
0&
#115000
13
b100001100 4
b110011001100110011001100110011 +
b110011001100110011001100110011 1
b100001100 $
b100001100 -
1&
#120000
0&
#125000
03
b1000100010001000100010001000100 +
b1000100010001000100010001000100 1
b0 *
b0 0
1&
#130000
0&
#135000
1!
b10 *
b10 0
0,
b11111111111111111111111111111111 $
b11111111111111111111111111111111 -
b0 %
b0 .
1&
#140000
0&
#145000
0!
b0 *
b0 0
1&
